{
	"id": "08efceed-bb8d-4c74-8ef5-982d1ee0ce70",
	"name": "QA",
	"values": [
		{
			"key": "CORE_IAM_BASE_PATH",
			"value": "https://pr-kd-az-stg-core-iam-api.azurewebsites.net/",
			"type": "default",
			"enabled": true
		},
		{
			"key": "GATEWAY_BASE_PATH",
			"value": "https://pr-kd-az-stg-gw-auth-api.azurewebsites.net/",
			"type": "default",
			"enabled": true
		},
		{
			"key": "CORE_RISK_BASE_PATH",
			"value": "https://pr-kd-az-stg-core-risks-api.azurewebsites.net/",
			"type": "default",
			"enabled": true
		},
		{
			"key": "INT_NOTO_BASE_PATH",
			"value": "https://pr-kd-az-stg-int-noto-api.azurewebsites.net/",
			"type": "default",
			"enabled": true
		}
	],
	"_postman_variable_scope": "environment",
	"_postman_exported_at": "2023-09-14T10:58:24.631Z",
	"_postman_exported_using": "Postman/10.17.7"
}